LICENSE.txt
MANIFEST.in
README.rst
setup.py
lod/TRUTH.txt
lod/__init__.py
lod/basics.py
lod/exceptions.py
lod/lod_tools.py
lod/utilities.py
lod/fibonacci/DESCRIPTION.txt
lod/fibonacci/Dockerfile
lod/fibonacci/app.py
lod/fibonacci/requirements.txt
lodtools.egg-info/PKG-INFO
lodtools.egg-info/SOURCES.txt
lodtools.egg-info/dependency_links.txt
lodtools.egg-info/entry_points.txt
lodtools.egg-info/requires.txt
lodtools.egg-info/top_level.txt