Metadata-Version: 1.0
Name: lodtools
Version: 1.0.76.dev1
Summary: A program for interacting with the API of LegionOfDevs.com
Home-page: https://legionofdevs.com
Author: Florian Dietz
Author-email: floriandietz44@gmail.com
License: MIT
Platform: UNKNOWN
